missil-0.1.7.dist-info/METADATA
missil-0.1.7.dist-info/WHEEL
missil-0.1.7.dist-info/licenses/LICENSE
missil/__init__.py
missil/bearers.py
missil/exceptions.py
missil/jwt_utilities.py
missil/routers.py
missil/rules.py
missil-0.1.7.dist-info/RECORD
